cloudburst/__about__.py
cloudburst/__init__.py
cloudburst/twitter.py
cloudburst/utils.py
cloudburst-0.1.9.dist-info/METADATA
cloudburst-0.1.9.dist-info/WHEEL
cloudburst-0.1.9.dist-info/licenses/LICENSE.md
cloudburst-0.1.9.dist-info/RECORD
