Metadata-Version: 2.1
Name: cloudburst
Version: 0.1.9
Summary: ⛈️ Gather data quickly and easily
Project-URL: Documentation, https://docs.cwdt.us/cloudburst
Project-URL: Issues, https://github.com/cwdt-us/cloudburst/issues
Project-URL: Source, https://github.com/cwdt-us/cloudburst
Author-email: "William W. Marx" <m94@marx.sh>
License:                                  Apache License
License-File: LICENSE.md
Classifier: Development Status :: 3 - Alpha
Classifier: Programming Language :: Python
Classifier: Programming Language :: Python :: 3.7
Classifier: Programming Language :: Python :: 3.8
Classifier: Programming Language :: Python :: 3.9
Classifier: Programming Language :: Python :: 3.10
Classifier: Programming Language :: Python :: 3.11
Classifier: Programming Language :: Python :: Implementation :: CPython
Classifier: Programming Language :: Python :: Implementation :: PyPy
Requires-Python: >=3.7
Requires-Dist: multiprocess
Requires-Dist: requests
